MANIFEST.in
README.txt
setup.cfg
setup.py
docs/HISTORY.txt
docs/INSTALL.txt
docs/LICENSE.GPL
docs/LICENSE.txt
plonetheme/__init__.py
plonetheme.cleantheme.egg-info/PKG-INFO
plonetheme.cleantheme.egg-info/SOURCES.txt
plonetheme.cleantheme.egg-info/dependency_links.txt
plonetheme.cleantheme.egg-info/entry_points.txt
plonetheme.cleantheme.egg-info/namespace_packages.txt
plonetheme.cleantheme.egg-info/not-zip-safe
plonetheme.cleantheme.egg-info/paster_plugins.txt
plonetheme.cleantheme.egg-info/requires.txt
plonetheme.cleantheme.egg-info/top_level.txt
plonetheme/cleantheme/__init__.py
plonetheme/cleantheme/configure.zcml
plonetheme/cleantheme/profiles.zcml
plonetheme/cleantheme/screenshot.png
plonetheme/cleantheme/skins.zcml
plonetheme/cleantheme/version.txt
plonetheme/cleantheme/browser/__init__.py
plonetheme/cleantheme/browser/configure.zcml
plonetheme/cleantheme/browser/interfaces.py
plonetheme/cleantheme/browser/site_actions.pt
plonetheme/cleantheme/browser/viewlets.py
plonetheme/cleantheme/browser/images/README.txt
plonetheme/cleantheme/browser/images/accessibility.gif
plonetheme/cleantheme/browser/images/arrow-black.png
plonetheme/cleantheme/browser/images/arrow-red.png
plonetheme/cleantheme/browser/images/button-green.gif
plonetheme/cleantheme/browser/images/button.gif
plonetheme/cleantheme/browser/images/envelope.gif
plonetheme/cleantheme/browser/images/globalnav-bg.png
plonetheme/cleantheme/browser/images/house.gif
plonetheme/cleantheme/browser/images/printer.gif
plonetheme/cleantheme/browser/images/rss.gif
plonetheme/cleantheme/browser/images/search-button-big.gif
plonetheme/cleantheme/browser/images/search-button.gif
plonetheme/cleantheme/browser/images/search-button_mid.gif
plonetheme/cleantheme/browser/images/sitemap.gif
plonetheme/cleantheme/browser/stylesheets/README.txt
plonetheme/cleantheme/browser/stylesheets/main.css
plonetheme/cleantheme/profiles/default/cssregistry.xml
plonetheme/cleantheme/profiles/default/metadata.xml
plonetheme/cleantheme/profiles/default/propertiestool.xml
plonetheme/cleantheme/profiles/default/skins.xml
plonetheme/cleantheme/skins/plonetheme_cleantheme_custom_images/CONTENT.txt
plonetheme/cleantheme/skins/plonetheme_cleantheme_custom_images/logo.jpg
plonetheme/cleantheme/skins/plonetheme_cleantheme_custom_templates/CONTENT.txt
plonetheme/cleantheme/skins/plonetheme_cleantheme_styles/CONTENT.txt
