Metadata-Version: 1.0
Name: plonetheme.cleantheme
Version: 0.1
Summary: An installable theme for Plone 3.0
Home-page: http://svn.plone.org/svn/collective/plonetheme.cleantheme
Author: Giorgio Borelli
Author-email: giorgio@giorgioborelli.it
License: GPL
Keywords: web zope plone theme
Platform: UNKNOWN
Classifier: Framework :: Plone
Classifier: Programming Language :: Python
Classifier: Topic :: Software Development :: Libraries :: Python Modules
